MANIFEST.in
README.md
VERSION.txt
build_bundled.sh
setup.cfg
setup.py
src/marian_sentencepiece.egg-info/PKG-INFO
src/marian_sentencepiece.egg-info/SOURCES.txt
src/marian_sentencepiece.egg-info/dependency_links.txt
src/marian_sentencepiece.egg-info/top_level.txt
src/sentencepiece/__init__.py
src/sentencepiece/sentencepiece.i
src/sentencepiece/sentencepiece_model_pb2.py
src/sentencepiece/sentencepiece_pb2.py
src/sentencepiece/sentencepiece_wrap.cxx
test/__init__.py
test/botchan.txt
test/sentencepiece_test.py
test/test_ja_model.model
test/test_model.model