Metadata-Version: 2.1
Name: marian-sentencepiece
Version: 0.1.94
Summary: Python wrapper for Marian NMT version of SentencePiece
Home-page: https://github.com/marian-nmt/sentencepiece
Author: Taku Kudo
Author-email: taku@google.com
License: Apache
Platform: Unix
Classifier: Development Status :: 5 - Production/Stable
Classifier: Environment :: Console
Classifier: Intended Audience :: Developers
Classifier: Intended Audience :: Science/Research
Classifier: License :: OSI Approved :: Apache Software License
Classifier: Operating System :: Unix
Classifier: Programming Language :: Python
Classifier: Topic :: Text Processing :: Linguistic
Classifier: Topic :: Software Development :: Libraries :: Python Modules
